pytket/extensions/projectq/__init__.py
pytket/extensions/projectq/_metadata.py
pytket/extensions/projectq/projectq_convert.py
pytket/extensions/projectq/py.typed
pytket/extensions/projectq/backends/__init__.py
pytket/extensions/projectq/backends/projectq_backend.py
pytket_projectq-0.39.0.dist-info/licenses/LICENSE
tests/projectq_backend_test.py
tests/projectq_convert_test.py
pytket_projectq-0.39.0.dist-info/METADATA
pytket_projectq-0.39.0.dist-info/WHEEL
pytket_projectq-0.39.0.dist-info/top_level.txt
pytket_projectq-0.39.0.dist-info/RECORD
